microverse/__init__.py
microverse/asynctestclient.py
microverse/contents.py
microverse/index.html
microverse/main.py
microverse/service-worker.js
microverse/to_thread.py
microverse-0.1.0.dist-info/METADATA
microverse-0.1.0.dist-info/WHEEL
microverse-0.1.0.dist-info/entry_points.txt
microverse-0.1.0.dist-info/licenses/LICENSE
microverse-0.1.0.dist-info/RECORD
